linalg_for_datasci/arrays.py
linalg_for_datasci/tests.py
linalg_for_datasci/utils.py
linalg_for_datasci/datasets/__init__.py
linalg_for_datasci/datasets/circuit_courts.csv
linalg_for_datasci/datasets/datasets.py
linalg_for_datasci/datasets/discretized_functions.csv
linalg_for_datasci/datasets/eastern_cities.csv
linalg_for_datasci/datasets/federal_reserve_districts.csv
linalg_for_datasci/datasets/iris.csv
linalg_for_datasci/datasets/metropolises.csv
linalg_for_datasci/datasets/mountains.csv
linalg_for_datasci/datasets/states.csv
linalg_for_datasci/datasets/students.csv
linalg_for_datasci/datasets/western_cities.csv
linalg_for_datasci/linear_func/__init__.py
linalg_for_datasci/linear_func/demo.py
linalg_for_datasci/linear_func/utils.py
linalg_for_datasci/plotting/__init__.py
linalg_for_datasci/plotting/histograms.py
linalg_for_datasci/plotting/monte_carlo.py
linalg_for_datasci/plotting/pca_2D.py
linalg_for_datasci/plotting/pca_3D.py
linalg_for_datasci/plotting/plotly.py
linalg_for_datasci/plotting/region.py
linalg_for_datasci/plotting/spectral_3D.py
linalg_for_datasci/plotting/two_dimensional.py
linalg_for_datasci/plotting/vectors.py
linalg_for_datasci/widgets/TODO_convert_to_ipywidgets.py
linalg_for_datasci/widgets/__init__.py
linalg_for_datasci/widgets/linear_functions.py
linalg_for_datasci/widgets/norms.py
linalg_for_datasci/widgets/updating_plots.py
linalg_for_datasci-1.2.2.dist-info/LICENSE
linalg_for_datasci-1.2.2.dist-info/METADATA
linalg_for_datasci-1.2.2.dist-info/WHEEL
linalg_for_datasci-1.2.2.dist-info/top_level.txt
linalg_for_datasci-1.2.2.dist-info/RECORD
