Metadata-Version: 2.1
Name: linalg-for-datasci
Version: 1.2.2
Summary: Code supporting the computational instruction for the course STAT 89A: Linear Algebra for Data Science at UC Berkeley
Home-page: https://gitlab.com/stat-89a/linalg_for_datasci
Author: William Krinsman
Author-email: krinsman@berkeley.edu
License: BSD
Platform: UNKNOWN
Classifier: Programming Language :: Python :: 3
Classifier: Programming Language :: Python :: 3.7
Classifier: License :: OSI Approved :: BSD License
Requires-Dist: ipywidgets
Requires-Dist: matplotlib
Requires-Dist: numpy
Requires-Dist: pandas
Requires-Dist: plotly
